setup.py
dict_cmp/__init__.py
dict_cmp/cmp.py
dict_cmp.egg-info/PKG-INFO
dict_cmp.egg-info/SOURCES.txt
dict_cmp.egg-info/dependency_links.txt
dict_cmp.egg-info/entry_points.txt
dict_cmp.egg-info/top_level.txt