Metadata-Version: 1.0
Name: dict-cmp
Version: 0.0.1
Summary: tesla dict校验库
Home-page: UNKNOWN
Author: oyj
Author-email: wisecsj@gmail.com
License: UNKNOWN
Platform: UNKNOWN
